rmrkl/__init__.py
rmrkl/agent.py
rmrkl/executor.py
rmrkl/output_parser.py
rmrkl/prompts.py
rmrkl/version.py
rmrkl-0.0.3.dist-info/LICENSE
rmrkl-0.0.3.dist-info/METADATA
rmrkl-0.0.3.dist-info/WHEEL
rmrkl-0.0.3.dist-info/top_level.txt
rmrkl-0.0.3.dist-info/RECORD
