Metadata-Version: 2.1
Name: rmrkl
Version: 0.0.3
Summary: Robust Modular Reasoning, Knowledge and Language agent that uses tools and retries on failure
Home-page: https://github.com/whitead/robust-mrkl
Author: Andrew White
Author-email: andrew.white@rochester.edu
License: MIT
Classifier: Programming Language :: Python :: 3
Classifier: License :: OSI Approved :: MIT License
License-File: LICENSE
Requires-Dist: langchain (>=0.0.157)
